curvelets/__init__.py
curvelets/_internal.py
curvelets/_version.py
curvelets/_version.pyi
curvelets/py.typed
curvelets/numpy/__init__.py
curvelets/numpy/_backward_transform.py
curvelets/numpy/_backward_transform_monogenic.py
curvelets/numpy/_forward_transform.py
curvelets/numpy/_meyerwavelet.py
curvelets/numpy/_riesz.py
curvelets/numpy/_typing.py
curvelets/numpy/_udct.py
curvelets/numpy/_udct_windows.py
curvelets/numpy/_utils.py
curvelets/plot/__init__.py
curvelets/plot/_curvelet.py
curvelets/plot/_matplotlib.py
curvelets/torch/__init__.py
curvelets/torch/_backward_transform.py
curvelets/torch/_forward_transform.py
curvelets/torch/_meyerwavelet.py
curvelets/torch/_riesz.py
curvelets/torch/_typing.py
curvelets/torch/_udct.py
curvelets/torch/_udct_module.py
curvelets/torch/_udct_windows.py
curvelets/torch/_utils.py
curvelets/utils/__init__.py
curvelets/utils/_utils.py
curvelets-1.1.dist-info/METADATA
curvelets-1.1.dist-info/WHEEL
curvelets-1.1.dist-info/licenses/AUTHORS.md
curvelets-1.1.dist-info/licenses/LICENSE
curvelets-1.1.dist-info/RECORD
