Metadata-Version: 2.4
Name: curvelets
Version: 1.1
Summary: Open source implementation of the uniform discrete curvelet transform in Python.
Project-URL: Homepage, https://github.com/cako/curvelets
Project-URL: Bug Tracker, https://github.com/cako/curvelets/issues
Project-URL: Discussions, https://github.com/cako/curvelets/discussions
Project-URL: Changelog, https://github.com/cako/curvelets/releases
Author-email: Carlos Alberto da Costa Filho <c.dacostaf@gmail.com>
License: Copyright 2026 Carlos Alberto da Costa Filho, Duy Nguyen
License-File: AUTHORS.md
License-File: LICENSE
Classifier: Development Status :: 5 - Production/Stable
Classifier: Intended Audience :: Developers
Classifier: Intended Audience :: Science/Research
Classifier: License :: OSI Approved :: MIT License
Classifier: Natural Language :: English
Classifier: Operating System :: OS Independent
Classifier: Programming Language :: Python
Classifier: Programming Language :: Python :: 3
Classifier: Programming Language :: Python :: 3 :: Only
Classifier: Programming Language :: Python :: 3.9
Classifier: Programming Language :: Python :: 3.10
Classifier: Programming Language :: Python :: 3.11
Classifier: Programming Language :: Python :: 3.12
Classifier: Programming Language :: Python :: 3.13
Classifier: Programming Language :: Python :: 3.14
Classifier: Topic :: Scientific/Engineering
Classifier: Topic :: Scientific/Engineering :: Image Processing
Classifier: Topic :: Scientific/Engineering :: Mathematics
Classifier: Typing :: Typed
Requires-Python: >=3.9
Requires-Dist: numpy>=1.20
Requires-Dist: typing-extensions; python_version <= '3.10'
Provides-Extra: dev
Requires-Dist: coverage>=7.7.0; extra == 'dev'
Requires-Dist: pytest-cov>=3; extra == 'dev'
Requires-Dist: pytest>=6; extra == 'dev'
Provides-Extra: docs
Requires-Dist: furo>=2023.08.17; extra == 'docs'
Requires-Dist: matplotlib; extra == 'docs'
Requires-Dist: myst-parser; extra == 'docs'
Requires-Dist: scikit-learn; extra == 'docs'
Requires-Dist: sphinx-autodoc-typehints; extra == 'docs'
Requires-Dist: sphinx-copybutton; extra == 'docs'
Requires-Dist: sphinx-gallery; extra == 'docs'
Requires-Dist: sphinx>=8.2.1; extra == 'docs'
Requires-Dist: sphinxcontrib-bibtex; extra == 'docs'
Provides-Extra: matplotlib
Requires-Dist: matplotlib; extra == 'matplotlib'
Provides-Extra: test
Requires-Dist: coverage>=7.7.0; extra == 'test'
Requires-Dist: matplotlib; extra == 'test'
Requires-Dist: pytest-cov>=3; extra == 'test'
Requires-Dist: pytest-timeout>=2.0; extra == 'test'
Requires-Dist: pytest>=6; extra == 'test'
Requires-Dist: torch; extra == 'test'
Provides-Extra: torch
Requires-Dist: torch; extra == 'torch'
